[{"l":["https://w3id.org/unterrichtsvideos.net/vocabs/learning_format/lf1","https://w3id.org/unterrichtsvideos.net/vocabs/learning_format/lf2","https://w3id.org/unterrichtsvideos.net/vocabs/learning_format/lf3","https://w3id.org/unterrichtsvideos.net/vocabs/learning_format/lf4"],"le":["https://w3id.org/unterrichtsvideos.net/vocabs/learning_format/lf1","https://w3id.org/unterrichtsvideos.net/vocabs/learning_format/lf2","https://w3id.org/unterrichtsvideos.net/vocabs/learning_format/lf3","https://w3id.org/unterrichtsvideos.net/vocabs/learning_format/lf4"],"ler":["https://w3id.org/unterrichtsvideos.net/vocabs/learning_format/lf1","https://w3id.org/unterrichtsvideos.net/vocabs/learning_format/lf2","https://w3id.org/unterrichtsvideos.net/vocabs/learning_format/lf3","https://w3id.org/unterrichtsvideos.net/vocabs/learning_format/lf4"],"lern":["https://w3id.org/unterrichtsvideos.net/vocabs/learning_format/lf1","https://w3id.org/unterrichtsvideos.net/vocabs/learning_format/lf2","https://w3id.org/unterrichtsvideos.net/vocabs/learning_format/lf3","https://w3id.org/unterrichtsvideos.net/vocabs/learning_format/lf4"],"lerna":["https://w3id.org/unterrichtsvideos.net/vocabs/learning_format/lf1","https://w3id.org/unterrichtsvideos.net/vocabs/learning_format/lf2","https://w3id.org/unterrichtsvideos.net/vocabs/learning_format/lf3","https://w3id.org/unterrichtsvideos.net/vocabs/learning_format/lf4"],"lernan":["https://w3id.org/unterrichtsvideos.net/vocabs/learning_format/lf1","https://w3id.org/unterrichtsvideos.net/vocabs/learning_format/lf2","https://w3id.org/unterrichtsvideos.net/vocabs/learning_format/lf3","https://w3id.org/unterrichtsvideos.net/vocabs/learning_format/lf4"],"lernang":["https://w3id.org/unterrichtsvideos.net/vocabs/learning_format/lf1","https://w3id.org/unterrichtsvideos.net/vocabs/learning_format/lf2","https://w3id.org/unterrichtsvideos.net/vocabs/learning_format/lf3","https://w3id.org/unterrichtsvideos.net/vocabs/learning_format/lf4"],"lernange":["https://w3id.org/unterrichtsvideos.net/vocabs/learning_format/lf1","https://w3id.org/unterrichtsvideos.net/vocabs/learning_format/lf2","https://w3id.org/unterrichtsvideos.net/vocabs/learning_format/lf3","https://w3id.org/unterrichtsvideos.net/vocabs/learning_format/lf4"],"lernangeb":["https://w3id.org/unterrichtsvideos.net/vocabs/learning_format/lf1","https://w3id.org/unterrichtsvideos.net/vocabs/learning_format/lf2","https://w3id.org/unterrichtsvideos.net/vocabs/learning_format/lf3","https://w3id.org/unterrichtsvideos.net/vocabs/learning_format/lf4"],"lernangebo":["https://w3id.org/unterrichtsvideos.net/vocabs/learning_format/lf1","https://w3id.org/unterrichtsvideos.net/vocabs/learning_format/lf2","https://w3id.org/unterrichtsvideos.net/vocabs/learning_format/lf3","https://w3id.org/unterrichtsvideos.net/vocabs/learning_format/lf4"],"lernangebot":["https://w3id.org/unterrichtsvideos.net/vocabs/learning_format/lf1","https://w3id.org/unterrichtsvideos.net/vocabs/learning_format/lf2","https://w3id.org/unterrichtsvideos.net/vocabs/learning_format/lf3","https://w3id.org/unterrichtsvideos.net/vocabs/learning_format/lf4"],"lernangebote":["https://w3id.org/unterrichtsvideos.net/vocabs/learning_format/lf1","https://w3id.org/unterrichtsvideos.net/vocabs/learning_format/lf2","https://w3id.org/unterrichtsvideos.net/vocabs/learning_format/lf3","https://w3id.org/unterrichtsvideos.net/vocabs/learning_format/lf4"]},{"d":["https://w3id.org/unterrichtsvideos.net/vocabs/learning_format/lf1","https://w3id.org/unterrichtsvideos.net/vocabs/learning_format/lf2","https://w3id.org/unterrichtsvideos.net/vocabs/learning_format/lf3","https://w3id.org/unterrichtsvideos.net/vocabs/learning_format/lf4"],"di":["https://w3id.org/unterrichtsvideos.net/vocabs/learning_format/lf1","https://w3id.org/unterrichtsvideos.net/vocabs/learning_format/lf2","https://w3id.org/unterrichtsvideos.net/vocabs/learning_format/lf3","https://w3id.org/unterrichtsvideos.net/vocabs/learning_format/lf4"],"die":["https://w3id.org/unterrichtsvideos.net/vocabs/learning_format/lf1","https://w3id.org/unterrichtsvideos.net/vocabs/learning_format/lf2","https://w3id.org/unterrichtsvideos.net/vocabs/learning_format/lf3","https://w3id.org/unterrichtsvideos.net/vocabs/learning_format/lf4"]},{"v":["https://w3id.org/unterrichtsvideos.net/vocabs/learning_format/lf1","https://w3id.org/unterrichtsvideos.net/vocabs/learning_format/lf2","https://w3id.org/unterrichtsvideos.net/vocabs/learning_format/lf4"],"vo":["https://w3id.org/unterrichtsvideos.net/vocabs/learning_format/lf1","https://w3id.org/unterrichtsvideos.net/vocabs/learning_format/lf2","https://w3id.org/unterrichtsvideos.net/vocabs/learning_format/lf4"],"vol":["https://w3id.org/unterrichtsvideos.net/vocabs/learning_format/lf1","https://w3id.org/unterrichtsvideos.net/vocabs/learning_format/lf2","https://w3id.org/unterrichtsvideos.net/vocabs/learning_format/lf4"],"voll":["https://w3id.org/unterrichtsvideos.net/vocabs/learning_format/lf1","https://w3id.org/unterrichtsvideos.net/vocabs/learning_format/lf2","https://w3id.org/unterrichtsvideos.net/vocabs/learning_format/lf4"],"volls":["https://w3id.org/unterrichtsvideos.net/vocabs/learning_format/lf1","https://w3id.org/unterrichtsvideos.net/vocabs/learning_format/lf2","https://w3id.org/unterrichtsvideos.net/vocabs/learning_format/lf4"],"vollst":["https://w3id.org/unterrichtsvideos.net/vocabs/learning_format/lf1","https://w3id.org/unterrichtsvideos.net/vocabs/learning_format/lf2","https://w3id.org/unterrichtsvideos.net/vocabs/learning_format/lf4"],"vollstä":["https://w3id.org/unterrichtsvideos.net/vocabs/learning_format/lf1","https://w3id.org/unterrichtsvideos.net/vocabs/learning_format/lf2","https://w3id.org/unterrichtsvideos.net/vocabs/learning_format/lf4"],"vollstän":["https://w3id.org/unterrichtsvideos.net/vocabs/learning_format/lf1","https://w3id.org/unterrichtsvideos.net/vocabs/learning_format/lf2","https://w3id.org/unterrichtsvideos.net/vocabs/learning_format/lf4"],"vollständ":["https://w3id.org/unterrichtsvideos.net/vocabs/learning_format/lf1","https://w3id.org/unterrichtsvideos.net/vocabs/learning_format/lf2","https://w3id.org/unterrichtsvideos.net/vocabs/learning_format/lf4"],"vollständi":["https://w3id.org/unterrichtsvideos.net/vocabs/learning_format/lf1","https://w3id.org/unterrichtsvideos.net/vocabs/learning_format/lf2","https://w3id.org/unterrichtsvideos.net/vocabs/learning_format/lf4"],"vollständig":["https://w3id.org/unterrichtsvideos.net/vocabs/learning_format/lf1","https://w3id.org/unterrichtsvideos.net/vocabs/learning_format/lf2","https://w3id.org/unterrichtsvideos.net/vocabs/learning_format/lf4"],"s":["https://w3id.org/unterrichtsvideos.net/vocabs/learning_format/lf3"],"so":["https://w3id.org/unterrichtsvideos.net/vocabs/learning_format/lf3"],"sow":["https://w3id.org/unterrichtsvideos.net/vocabs/learning_format/lf3"],"sowo":["https://w3id.org/unterrichtsvideos.net/vocabs/learning_format/lf3"],"sowoh":["https://w3id.org/unterrichtsvideos.net/vocabs/learning_format/lf3"],"sowohl":["https://w3id.org/unterrichtsvideos.net/vocabs/learning_format/lf3"],"p":["https://w3id.org/unterrichtsvideos.net/vocabs/learning_format/lf3"],"pr":["https://w3id.org/unterrichtsvideos.net/vocabs/learning_format/lf3"],"prä":["https://w3id.org/unterrichtsvideos.net/vocabs/learning_format/lf3"],"präs":["https://w3id.org/unterrichtsvideos.net/vocabs/learning_format/lf3"],"präse":["https://w3id.org/unterrichtsvideos.net/vocabs/learning_format/lf3"],"präsen":["https://w3id.org/unterrichtsvideos.net/vocabs/learning_format/lf3"],"präsenz":["https://w3id.org/unterrichtsvideos.net/vocabs/learning_format/lf3"]},{"i":["https://w3id.org/unterrichtsvideos.net/vocabs/learning_format/lf1"],"in":["https://w3id.org/unterrichtsvideos.net/vocabs/learning_format/lf1"],"o":["https://w3id.org/unterrichtsvideos.net/vocabs/learning_format/lf2","https://w3id.org/unterrichtsvideos.net/vocabs/learning_format/lf4"],"on":["https://w3id.org/unterrichtsvideos.net/vocabs/learning_format/lf2","https://w3id.org/unterrichtsvideos.net/vocabs/learning_format/lf4"],"onl":["https://w3id.org/unterrichtsvideos.net/vocabs/learning_format/lf2","https://w3id.org/unterrichtsvideos.net/vocabs/learning_format/lf4"],"onli":["https://w3id.org/unterrichtsvideos.net/vocabs/learning_format/lf2","https://w3id.org/unterrichtsvideos.net/vocabs/learning_format/lf4"],"onlin":["https://w3id.org/unterrichtsvideos.net/vocabs/learning_format/lf2","https://w3id.org/unterrichtsvideos.net/vocabs/learning_format/lf4"],"online":["https://w3id.org/unterrichtsvideos.net/vocabs/learning_format/lf2","https://w3id.org/unterrichtsvideos.net/vocabs/learning_format/lf4"],"a":["https://w3id.org/unterrichtsvideos.net/vocabs/learning_format/lf3"],"al":["https://w3id.org/unterrichtsvideos.net/vocabs/learning_format/lf3"],"als":["https://w3id.org/unterrichtsvideos.net/vocabs/learning_format/lf3"],"au":["https://w3id.org/unterrichtsvideos.net/vocabs/learning_format/lf3"],"auc":["https://w3id.org/unterrichtsvideos.net/vocabs/learning_format/lf3"],"auch":["https://w3id.org/unterrichtsvideos.net/vocabs/learning_format/lf3"]},{"p":["https://w3id.org/unterrichtsvideos.net/vocabs/learning_format/lf1"],"pr":["https://w3id.org/unterrichtsvideos.net/vocabs/learning_format/lf1"],"prä":["https://w3id.org/unterrichtsvideos.net/vocabs/learning_format/lf1"],"präs":["https://w3id.org/unterrichtsvideos.net/vocabs/learning_format/lf1"],"präse":["https://w3id.org/unterrichtsvideos.net/vocabs/learning_format/lf1"],"präsen":["https://w3id.org/unterrichtsvideos.net/vocabs/learning_format/lf1"],"präsenz":["https://w3id.org/unterrichtsvideos.net/vocabs/learning_format/lf1"],"u":["https://w3id.org/unterrichtsvideos.net/vocabs/learning_format/lf2"],"un":["https://w3id.org/unterrichtsvideos.net/vocabs/learning_format/lf2"],"und":["https://w3id.org/unterrichtsvideos.net/vocabs/learning_format/lf2"],"o":["https://w3id.org/unterrichtsvideos.net/vocabs/learning_format/lf3"],"on":["https://w3id.org/unterrichtsvideos.net/vocabs/learning_format/lf3"],"onl":["https://w3id.org/unterrichtsvideos.net/vocabs/learning_format/lf3"],"onli":["https://w3id.org/unterrichtsvideos.net/vocabs/learning_format/lf3"],"onlin":["https://w3id.org/unterrichtsvideos.net/vocabs/learning_format/lf3"],"online":["https://w3id.org/unterrichtsvideos.net/vocabs/learning_format/lf3"],"s":["https://w3id.org/unterrichtsvideos.net/vocabs/learning_format/lf4"],"st":["https://w3id.org/unterrichtsvideos.net/vocabs/learning_format/lf4"],"sta":["https://w3id.org/unterrichtsvideos.net/vocabs/learning_format/lf4"],"stat":["https://w3id.org/unterrichtsvideos.net/vocabs/learning_format/lf4"],"statt":["https://w3id.org/unterrichtsvideos.net/vocabs/learning_format/lf4"],"stattf":["https://w3id.org/unterrichtsvideos.net/vocabs/learning_format/lf4"],"stattfi":["https://w3id.org/unterrichtsvideos.net/vocabs/learning_format/lf4"],"stattfin":["https://w3id.org/unterrichtsvideos.net/vocabs/learning_format/lf4"],"stattfind":["https://w3id.org/unterrichtsvideos.net/vocabs/learning_format/lf4"],"stattfinde":["https://w3id.org/unterrichtsvideos.net/vocabs/learning_format/lf4"],"stattfinden":["https://w3id.org/unterrichtsvideos.net/vocabs/learning_format/lf4"]},{"s":["https://w3id.org/unterrichtsvideos.net/vocabs/learning_format/lf1"],"st":["https://w3id.org/unterrichtsvideos.net/vocabs/learning_format/lf1"],"sta":["https://w3id.org/unterrichtsvideos.net/vocabs/learning_format/lf1"],"stat":["https://w3id.org/unterrichtsvideos.net/vocabs/learning_format/lf1"],"statt":["https://w3id.org/unterrichtsvideos.net/vocabs/learning_format/lf1"],"stattf":["https://w3id.org/unterrichtsvideos.net/vocabs/learning_format/lf1"],"stattfi":["https://w3id.org/unterrichtsvideos.net/vocabs/learning_format/lf1"],"stattfin":["https://w3id.org/unterrichtsvideos.net/vocabs/learning_format/lf1"],"stattfind":["https://w3id.org/unterrichtsvideos.net/vocabs/learning_format/lf1"],"stattfinde":["https://w3id.org/unterrichtsvideos.net/vocabs/learning_format/lf1"],"stattfinden":["https://w3id.org/unterrichtsvideos.net/vocabs/learning_format/lf1"],"i":["https://w3id.org/unterrichtsvideos.net/vocabs/learning_format/lf2"],"im":["https://w3id.org/unterrichtsvideos.net/vocabs/learning_format/lf2"],"e":["https://w3id.org/unterrichtsvideos.net/vocabs/learning_format/lf3"],"el":["https://w3id.org/unterrichtsvideos.net/vocabs/learning_format/lf3"],"ele":["https://w3id.org/unterrichtsvideos.net/vocabs/learning_format/lf3"],"elem":["https://w3id.org/unterrichtsvideos.net/vocabs/learning_format/lf3"],"eleme":["https://w3id.org/unterrichtsvideos.net/vocabs/learning_format/lf3"],"elemen":["https://w3id.org/unterrichtsvideos.net/vocabs/learning_format/lf3"],"element":["https://w3id.org/unterrichtsvideos.net/vocabs/learning_format/lf3"],"elemente":["https://w3id.org/unterrichtsvideos.net/vocabs/learning_format/lf3"],"k":["https://w3id.org/unterrichtsvideos.net/vocabs/learning_format/lf3"],"ko":["https://w3id.org/unterrichtsvideos.net/vocabs/learning_format/lf3"],"kom":["https://w3id.org/unterrichtsvideos.net/vocabs/learning_format/lf3"],"komb":["https://w3id.org/unterrichtsvideos.net/vocabs/learning_format/lf3"],"kombi":["https://w3id.org/unterrichtsvideos.net/vocabs/learning_format/lf3"],"kombin":["https://w3id.org/unterrichtsvideos.net/vocabs/learning_format/lf3"],"kombini":["https://w3id.org/unterrichtsvideos.net/vocabs/learning_format/lf3"],"kombinie":["https://w3id.org/unterrichtsvideos.net/vocabs/learning_format/lf3"],"kombinier":["https://w3id.org/unterrichtsvideos.net/vocabs/learning_format/lf3"],"kombiniere":["https://w3id.org/unterrichtsvideos.net/vocabs/learning_format/lf3"],"kombinieren":["https://w3id.org/unterrichtsvideos.net/vocabs/learning_format/lf3"],"a":["https://w3id.org/unterrichtsvideos.net/vocabs/learning_format/lf4"],"ab":["https://w3id.org/unterrichtsvideos.net/vocabs/learning_format/lf4"],"abe":["https://w3id.org/unterrichtsvideos.net/vocabs/learning_format/lf4"],"aber":["https://w3id.org/unterrichtsvideos.net/vocabs/learning_format/lf4"],"f":["https://w3id.org/unterrichtsvideos.net/vocabs/learning_format/lf4"],"fe":["https://w3id.org/unterrichtsvideos.net/vocabs/learning_format/lf4"],"fes":["https://w3id.org/unterrichtsvideos.net/vocabs/learning_format/lf4"],"fest":["https://w3id.org/unterrichtsvideos.net/vocabs/learning_format/lf4"],"feste":["https://w3id.org/unterrichtsvideos.net/vocabs/learning_format/lf4"]},{"s":["https://w3id.org/unterrichtsvideos.net/vocabs/learning_format/lf2"],"se":["https://w3id.org/unterrichtsvideos.net/vocabs/learning_format/lf2"],"sel":["https://w3id.org/unterrichtsvideos.net/vocabs/learning_format/lf2"],"selb":["https://w3id.org/unterrichtsvideos.net/vocabs/learning_format/lf2"],"selbs":["https://w3id.org/unterrichtsvideos.net/vocabs/learning_format/lf2"],"selbst":["https://w3id.org/unterrichtsvideos.net/vocabs/learning_format/lf2"],"selbsts":["https://w3id.org/unterrichtsvideos.net/vocabs/learning_format/lf2"],"selbstst":["https://w3id.org/unterrichtsvideos.net/vocabs/learning_format/lf2"],"selbststu":["https://w3id.org/unterrichtsvideos.net/vocabs/learning_format/lf2"],"selbststud":["https://w3id.org/unterrichtsvideos.net/vocabs/learning_format/lf2"],"selbststudi":["https://w3id.org/unterrichtsvideos.net/vocabs/learning_format/lf2"],"selbststudiu":["https://w3id.org/unterrichtsvideos.net/vocabs/learning_format/lf2"],"selbststudium":["https://w3id.org/unterrichtsvideos.net/vocabs/learning_format/lf2"],"u":["https://w3id.org/unterrichtsvideos.net/vocabs/learning_format/lf3"],"un":["https://w3id.org/unterrichtsvideos.net/vocabs/learning_format/lf3"],"und":["https://w3id.org/unterrichtsvideos.net/vocabs/learning_format/lf3"],"f":["https://w3id.org/unterrichtsvideos.net/vocabs/learning_format/lf3"],"fe":["https://w3id.org/unterrichtsvideos.net/vocabs/learning_format/lf3"],"fes":["https://w3id.org/unterrichtsvideos.net/vocabs/learning_format/lf3"],"fest":["https://w3id.org/unterrichtsvideos.net/vocabs/learning_format/lf3"],"feste":["https://w3id.org/unterrichtsvideos.net/vocabs/learning_format/lf3"],"g":["https://w3id.org/unterrichtsvideos.net/vocabs/learning_format/lf4"],"gr":["https://w3id.org/unterrichtsvideos.net/vocabs/learning_format/lf4"],"gru":["https://w3id.org/unterrichtsvideos.net/vocabs/learning_format/lf4"],"grup":["https://w3id.org/unterrichtsvideos.net/vocabs/learning_format/lf4"],"grupp":["https://w3id.org/unterrichtsvideos.net/vocabs/learning_format/lf4"],"gruppe":["https://w3id.org/unterrichtsvideos.net/vocabs/learning_format/lf4"],"gruppen":["https://w3id.org/unterrichtsvideos.net/vocabs/learning_format/lf4"],"gruppent":["https://w3id.org/unterrichtsvideos.net/vocabs/learning_format/lf4"],"gruppente":["https://w3id.org/unterrichtsvideos.net/vocabs/learning_format/lf4"],"gruppenter":["https://w3id.org/unterrichtsvideos.net/vocabs/learning_format/lf4"],"gruppenterm":["https://w3id.org/unterrichtsvideos.net/vocabs/learning_format/lf4"],"gruppentermi":["https://w3id.org/unterrichtsvideos.net/vocabs/learning_format/lf4"],"gruppentermin":["https://w3id.org/unterrichtsvideos.net/vocabs/learning_format/lf4"],"gruppentermine":["https://w3id.org/unterrichtsvideos.net/vocabs/learning_format/lf4"]},{"st":["https://w3id.org/unterrichtsvideos.net/vocabs/learning_format/lf2"],"sta":["https://w3id.org/unterrichtsvideos.net/vocabs/learning_format/lf2"],"stat":["https://w3id.org/unterrichtsvideos.net/vocabs/learning_format/lf2"],"statt":["https://w3id.org/unterrichtsvideos.net/vocabs/learning_format/lf2"],"stattf":["https://w3id.org/unterrichtsvideos.net/vocabs/learning_format/lf2"],"stattfi":["https://w3id.org/unterrichtsvideos.net/vocabs/learning_format/lf2"],"stattfin":["https://w3id.org/unterrichtsvideos.net/vocabs/learning_format/lf2"],"stattfind":["https://w3id.org/unterrichtsvideos.net/vocabs/learning_format/lf2"],"stattfinde":["https://w3id.org/unterrichtsvideos.net/vocabs/learning_format/lf2"],"stattfinden":["https://w3id.org/unterrichtsvideos.net/vocabs/learning_format/lf2"],"g":["https://w3id.org/unterrichtsvideos.net/vocabs/learning_format/lf3"],"gr":["https://w3id.org/unterrichtsvideos.net/vocabs/learning_format/lf3"],"gru":["https://w3id.org/unterrichtsvideos.net/vocabs/learning_format/lf3"],"grup":["https://w3id.org/unterrichtsvideos.net/vocabs/learning_format/lf3"],"grupp":["https://w3id.org/unterrichtsvideos.net/vocabs/learning_format/lf3"],"gruppe":["https://w3id.org/unterrichtsvideos.net/vocabs/learning_format/lf3"],"gruppen":["https://w3id.org/unterrichtsvideos.net/vocabs/learning_format/lf3"],"gruppent":["https://w3id.org/unterrichtsvideos.net/vocabs/learning_format/lf3"],"gruppente":["https://w3id.org/unterrichtsvideos.net/vocabs/learning_format/lf3"],"gruppenter":["https://w3id.org/unterrichtsvideos.net/vocabs/learning_format/lf3"],"gruppenterm":["https://w3id.org/unterrichtsvideos.net/vocabs/learning_format/lf3"],"gruppentermi":["https://w3id.org/unterrichtsvideos.net/vocabs/learning_format/lf3"],"gruppentermin":["https://w3id.org/unterrichtsvideos.net/vocabs/learning_format/lf3"],"gruppentermine":["https://w3id.org/unterrichtsvideos.net/vocabs/learning_format/lf3"],"h":["https://w3id.org/unterrichtsvideos.net/vocabs/learning_format/lf3","https://w3id.org/unterrichtsvideos.net/vocabs/learning_format/lf4"],"ha":["https://w3id.org/unterrichtsvideos.net/vocabs/learning_format/lf3","https://w3id.org/unterrichtsvideos.net/vocabs/learning_format/lf4"],"hab":["https://w3id.org/unterrichtsvideos.net/vocabs/learning_format/lf3","https://w3id.org/unterrichtsvideos.net/vocabs/learning_format/lf4"],"habe":["https://w3id.org/unterrichtsvideos.net/vocabs/learning_format/lf3","https://w3id.org/unterrichtsvideos.net/vocabs/learning_format/lf4"],"haben":["https://w3id.org/unterrichtsvideos.net/vocabs/learning_format/lf3","https://w3id.org/unterrichtsvideos.net/vocabs/learning_format/lf4"]},{}]